dilog/__init__.py
dilog/logger.py
dilog/logging_config.yaml
dilog/upload_log.py
dlog/__init__.py
dlog/logger.py
dlog/upload_log.py
dilog-0.1.6.dist-info/LICENSE
dilog-0.1.6.dist-info/METADATA
dilog-0.1.6.dist-info/WHEEL
dilog-0.1.6.dist-info/top_level.txt
dilog-0.1.6.dist-info/RECORD
