Metadata-Version: 2.1
Name: dilog
Version: 0.1.6
Summary: 私有的log以及log的oss上传包
Home-page: https://gitee.com/didi_nj/dilog
Author: didiwangluo
Author-email: didiwangluo@outlook.com
Classifier: Programming Language :: Python :: 3
Classifier: License :: OSI Approved :: MIT License
Classifier: Operating System :: OS Independent
Requires-Python: >=3.6
License-File: LICENSE
Requires-Dist: PyYAML >=5.3.1
Requires-Dist: oss2 >=2.13.0
